entoolkit/__init__.py
entoolkit/toolkit.py
entoolkit/epanet/Darwin/libepanet.dylib
entoolkit/epanet/Linux/libepanet2_amd64.so
entoolkit/epanet/Windows/EN2setup.exe
entoolkit/epanet/Windows/epanet2.bas
entoolkit/epanet/Windows/epanet2.def
entoolkit/epanet/Windows/epanet2.dll
entoolkit/epanet/Windows/epanet2.lib
entoolkit/epanet/Windows/epanet2.pas
entoolkit/epanet/Windows/epanet2_amd64.dll
entoolkit-0.0.15.dist-info/LICENSE
entoolkit-0.0.15.dist-info/METADATA
entoolkit-0.0.15.dist-info/WHEEL
entoolkit-0.0.15.dist-info/top_level.txt
entoolkit-0.0.15.dist-info/RECORD
