Metadata-Version: 2.1
Name: entoolkit
Version: 0.0.15
Summary: Epanet Toolkit Wrapper for Python
Home-page: https://github.com/andresgciamtez/entoolkit
Author: Andrés García Martínez
Author-email: ppnoptimizer@gmail.com
License: UNKNOWN
Platform: UNKNOWN
Classifier: Programming Language :: Python :: 3
Classifier: License :: OSI Approved :: GNU General Public License v2 (GPLv2)
Classifier: Operating System :: OS Independent
